setup.cfg
setup.py
tbs_client/__init__.py
tbs_client/api_client.py
tbs_client/configuration.py
tbs_client/rest.py
tbs_client/apis/__init__.py
tbs_client/apis/auth_api.py
tbs_client/apis/billing_api.py
tbs_client/apis/deployments_api.py
tbs_client/apis/hosts_api.py
tbs_client/apis/notifications_api.py
tbs_client/apis/projects_api.py
tbs_client/apis/search_api.py
tbs_client/apis/servers_api.py
tbs_client/apis/users_api.py
tbs_client/models/__init__.py
tbs_client/models/action.py
tbs_client/models/auth_token.py
tbs_client/models/auth_token_data.py
tbs_client/models/auth_token_error.py
tbs_client/models/card.py
tbs_client/models/card_data_post.py
tbs_client/models/card_data_putand_patch.py
tbs_client/models/card_error.py
tbs_client/models/card_update_error.py
tbs_client/models/collaborator.py
tbs_client/models/collaborator_data.py
tbs_client/models/collaborator_error.py
tbs_client/models/customer.py
tbs_client/models/customer_data.py
tbs_client/models/customer_error.py
tbs_client/models/deployment.py
tbs_client/models/deployment_config.py
tbs_client/models/deployment_data.py
tbs_client/models/docker_host.py
tbs_client/models/docker_host_data.py
tbs_client/models/docker_host_error.py
tbs_client/models/email.py
tbs_client/models/email_data.py
tbs_client/models/email_error.py
tbs_client/models/invoice.py
tbs_client/models/invoice_item.py
tbs_client/models/jwt.py
tbs_client/models/jwt_data.py
tbs_client/models/jwt_error.py
tbs_client/models/not_found.py
tbs_client/models/notification.py
tbs_client/models/notification_error.py
tbs_client/models/notification_list_update_data.py
tbs_client/models/notification_settings.py
tbs_client/models/notification_settings_data.py
tbs_client/models/notification_settings_error.py
tbs_client/models/notification_update_data.py
tbs_client/models/plan.py
tbs_client/models/plan_data.py
tbs_client/models/plan_error.py
tbs_client/models/project.py
tbs_client/models/project_copy_data.py
tbs_client/models/project_copy_data_1.py
tbs_sdk.egg-info/PKG-INFO
tbs_sdk.egg-info/SOURCES.txt
tbs_sdk.egg-info/dependency_links.txt
tbs_sdk.egg-info/requires.txt
tbs_sdk.egg-info/top_level.txt
