Metadata-Version: 1.1
Name: tbs-sdk
Version: 0.0.7
Summary: 3blades API
Home-page: https://github.com/3Blades/python-sdk
Author: UNKNOWN
Author-email: jgriebel@3blades.io
License: UNKNOWN
Download-URL: https://github.com/3Blades/python-sdk/archive/0.0.7.tar.gz
Keywords: 3blades API,Data Science
Platform: UNKNOWN
